LICENSE.txt
README.md
setup.cfg
setup.py
MarinetteSEFAZ.egg-info/PKG-INFO
MarinetteSEFAZ.egg-info/SOURCES.txt
MarinetteSEFAZ.egg-info/dependency_links.txt
MarinetteSEFAZ.egg-info/top_level.txt
marinetteSEFAZ/__init__.py
marinetteSEFAZ/excel.py
marinetteSEFAZ/seiRJ.py
marinetteSEFAZ/siafeRIO.py