Metadata-Version: 2.1
Name: MarinetteSEFAZ
Version: 2.0.0
Summary: Acesso ao SEI-RJ, siafeRIO e outras
Author: Joao Campbell
Author-email: joao.pedro.campbell@fazenda.rj.gov.br
License: MIT
Keywords: marinette
Classifier: Development Status :: 5 - Production/Stable
Classifier: Intended Audience :: Developers
Classifier: License :: OSI Approved :: MIT License
Classifier: Natural Language :: Portuguese (Brazilian)
Classifier: Operating System :: OS Independent
Classifier: Topic :: Software Development :: Internationalization
Classifier: Topic :: Scientific/Engineering :: Physics
License-File: LICENSE.txt
